DLScanner/__init__.py
DLScanner/gen_scanner.py
DLScanner/hep/__init__.py
DLScanner/hep/MicrOMEGAs/ML.py
DLScanner/hep/MicrOMEGAs/__init__.py
DLScanner/hep/MicrOMEGAs/micromegas_ML.py
DLScanner/hep/MicrOMEGAs/utils_megas.py
DLScanner/hep/MicrOMEGAs/vegas_S.py
DLScanner/hep/SPheno/ML.py
DLScanner/hep/SPheno/SPheno.py
DLScanner/hep/SPheno/SPheno_trial.py
DLScanner/hep/SPheno/SPheno_trial_regressor.py
DLScanner/hep/SPheno/__init__.py
DLScanner/hep/SPheno/utils.py
DLScanner/hep/SPheno/vegas_S.py
DLScanner/samplers/ML.py
DLScanner/samplers/__init__.py
DLScanner/utilities/__init__.py
DLScanner/utilities/plot.py
DLScanner/utilities/try_imports.py
DLScanner/utilities/vegas.py
DLScanner-1.0.0.dist-info/METADATA
DLScanner-1.0.0.dist-info/WHEEL
DLScanner-1.0.0.dist-info/top_level.txt
DLScanner-1.0.0.dist-info/RECORD
