Metadata-Version: 2.1
Name: DLScanner
Version: 1.0.0
Summary: Scanning parameter spaces using deep learning
Maintainer: Ahmed Hammad, Raymundo Ramos
Project-URL: Homepage, https://github.com/raalraan/DLScanner
Project-URL: Issues, https://github.com/raalraan/DLScanner/issues
Classifier: Programming Language :: Python :: 3
Classifier: License :: OSI Approved :: MIT License
Classifier: Operating System :: OS Independent
Requires-Python: >=3.9
Requires-Dist: numpy<2.0.0,>=1.23.5
Requires-Dist: vegas>=6.1
Requires-Dist: matplotlib
Requires-Dist: scikit-learn
